sd_geninfo/__init__.py
sd_geninfo/sd_geninfo.py
sd_geninfo/yaml_highlighter.py
sd_geninfo-0.0.3.dist-info/LICENSE
sd_geninfo-0.0.3.dist-info/METADATA
sd_geninfo-0.0.3.dist-info/WHEEL
sd_geninfo-0.0.3.dist-info/entry_points.txt
sd_geninfo-0.0.3.dist-info/top_level.txt
sd_geninfo-0.0.3.dist-info/RECORD
