Metadata-Version: 2.1
Name: sd-geninfo
Version: 0.0.3
Summary: Python CLI for reading metadata embedded in images generated by Stable Diffusion.
Home-page: https://github.com/coryg89/sd-geninfo
Author: Cory Gross
Author-email: coryg89@gmail.com
Project-URL: Bug Tracker, https://github.com/coryg89/sd-geninfo/issues
Classifier: Programming Language :: Python :: 3
Classifier: License :: OSI Approved :: MIT License
Classifier: Operating System :: OS Independent
Requires-Python: >=3.6
License-File: LICENSE
Requires-Dist: imageio
Requires-Dist: pillow
Requires-Dist: piexif
Requires-Dist: rich
Requires-Dist: pyyaml
